Metadata-Version: 2.4
Name: django-career-app
Version: 0.2.4
Summary: A Django project for a career portal.
Author-email: Your Name <you@example.com>
License: MIT License
Project-URL: Homepage, https://github.com/t6830/django-career-app
Project-URL: Repository, https://github.com/t6830/django-career-app
Classifier: Development Status :: 3 - Alpha
Classifier: Framework :: Django
Classifier: Intended Audience :: Developers
Classifier: License :: OSI Approved :: MIT License
Classifier: Programming Language :: Python :: 3
Classifier: Programming Language :: Python :: 3.9
Classifier: Programming Language :: Python :: 3.10
Classifier: Programming Language :: Python :: 3.11
Classifier: Programming Language :: Python :: 3.12
Classifier: Programming Language :: Python :: 3.13
Requires-Python: >=3.9
License-File: LICENSE
Requires-Dist: boto3
Requires-Dist: Django
Requires-Dist: django-storages
Requires-Dist: google-cloud-storage
Requires-Dist: json_repair
Requires-Dist: litellm
Requires-Dist: markdown2
Requires-Dist: pdfminer.six
Requires-Dist: python-decouple
Requires-Dist: python-dotenv
Requires-Dist: urllib3
Dynamic: license-file
